CHANGES.rst
DESCRIPTION.rst
LICENSE
MANIFEST.in
README.md
setup.py
src/image_complete/__init__.py
src/image_complete/auto.py
src/image_complete/base.py
src/image_complete/bmp.py
src/image_complete/gif.py
src/image_complete/jpg.py
src/image_complete/png.py
src/image_complete/webp.py
src/python_image_complete.egg-info/PKG-INFO
src/python_image_complete.egg-info/SOURCES.txt
src/python_image_complete.egg-info/dependency_links.txt
src/python_image_complete.egg-info/top_level.txt