Metadata-Version: 2.1
Name: python-image-complete
Version: 0.0.4
Summary: Python3 library for checking whether images are complete.
Home-page: https://github.com/waikato-datamining/python-image-complete
Author: Peter Reutemann
Author-email: fracpete@waikato.ac.nz
License: MIT License
Classifier: Development Status :: 4 - Beta
Classifier: License :: OSI Approved :: MIT License
Classifier: Topic :: Multimedia :: Graphics
Classifier: Programming Language :: Python :: 3
License-File: LICENSE
